{
  "!type": "Form",
  "HTML": null,
  "attributes": "",
  "background": "",
  "backgroundimage": "",
  "borderColor": "",
  "borderStyle": "",
  "borderWidth": "",
  "cached_js": null,
  "cached_js_script_hash": null,
  "children": [
    {
      "!type": "External",
      "file": [
        "forms",
        "ABMadLibs",
        "Elements",
        "Noun.json"
      ]
    },
    {
      "!type": "External",
      "file": [
        "forms",
        "ABMadLibs",
        "Elements",
        "enterName.json"
      ]
    },
    {
      "!type": "External",
      "file": [
        "forms",
        "ABMadLibs",
        "Elements",
        "Verb.json"
      ]
    },
    {
      "!type": "External",
      "file": [
        "forms",
        "ABMadLibs",
        "Elements",
        "Adverb.json"
      ]
    },
    {
      "!type": "External",
      "file": [
        "forms",
        "ABMadLibs",
        "Elements",
        "Adjective.json"
      ]
    },
    {
      "!type": "External",
      "file": [
        "forms",
        "ABMadLibs",
        "Elements",
        "inptDog.json"
      ]
    },
    {
      "!type": "External",
      "file": [
        "forms",
        "ABMadLibs",
        "Elements",
        "inptCat.json"
      ]
    },
    {
      "!type": "External",
      "file": [
        "forms",
        "ABMadLibs",
        "Elements",
        "inptHorse.json"
      ]
    },
    {
      "!type": "External",
      "file": [
        "forms",
        "ABMadLibs",
        "Elements",
        "inputRunning.json"
      ]
    },
    {
      "!type": "External",
      "file": [
        "forms",
        "ABMadLibs",
        "Elements",
        "inputJumping.json"
      ]
    },
    {
      "!type": "External",
      "file": [
        "forms",
        "ABMadLibs",
        "Elements",
        "inptWalking.json"
      ]
    },
    {
      "!type": "External",
      "file": [
        "forms",
        "ABMadLibs",
        "Elements",
        "inptBeautiful.json"
      ]
    },
    {
      "!type": "External",
      "file": [
        "forms",
        "ABMadLibs",
        "Elements",
        "inptFun.json"
      ]
    },
    {
      "!type": "External",
      "file": [
        "forms",
        "ABMadLibs",
        "Elements",
        "inptSad.json"
      ]
    },
    {
      "!type": "External",
      "file": [
        "forms",
        "ABMadLibs",
        "Elements",
        "inptLively.json"
      ]
    },
    {
      "!type": "External",
      "file": [
        "forms",
        "ABMadLibs",
        "Elements",
        "inptLoudly.json"
      ]
    },
    {
      "!type": "External",
      "file": [
        "forms",
        "ABMadLibs",
        "Elements",
        "inptCleverly.json"
      ]
    },
    {
      "!type": "External",
      "file": [
        "forms",
        "ABMadLibs",
        "Elements",
        "Resubmit.json"
      ]
    }
  ],
  "class": "",
  "designHeight": 0,
  "designWidth": 0,
  "expanded_pmp": null,
  "fullScreen": "true",
  "height": 460,
  "id": "ABMadLibs",
  "language": "JavaScript",
  "left": "0",
  "locked": false,
  "modal": "false",
  "onhide": "",
  "onkeypress": "",
  "onresize": "",
  "onshow": "",
  "openMode": "none",
  "parentForm": "",
  "position": "absolute",
  "script": null,
  "setFocusID": "",
  "style": "",
  "theme": "",
  "top": "0",
  "width": 320
}